poliwrap/__init__.py
poliwrap/onnx.py
poliwrap/policy.py
poliwrap/py.typed
poliwrap/torch.py
poliwrap-0.0.4.dist-info/WHEEL
poliwrap-0.0.4.dist-info/METADATA
poliwrap-0.0.4.dist-info/RECORD
