Metadata-Version: 2.3
Name: poliwrap
Version: 0.0.4
Summary: A lightweight, framework-agnostic abstraction for reinforcement learning policy inference.
Author: Miguel Villa Floran, Jing Cao
Author-email: Miguel Villa Floran <miguel.villafloran@gmail.com>, Jing Cao <jcao0715@gmail.com>
License: MIT License
Requires-Dist: numpy>=2.2.6
Requires-Dist: onnxruntime>=1.16.0 ; extra == 'onnx'
Requires-Dist: torch>=2.10.0 ; extra == 'torch'
Requires-Python: >=3.10
Provides-Extra: onnx
Provides-Extra: torch
